setup.py
pyrewriter/__init__.py
pyrewriter/grammar.py
pyrewriter/info.py
pyrewriter/parse.py
pyrewriter/predefined.py
pyrewriter/predefined_nginx.py
pyrewriter/token.py
pyrewriter.egg-info/PKG-INFO
pyrewriter.egg-info/SOURCES.txt
pyrewriter.egg-info/dependency_links.txt
pyrewriter.egg-info/requires.txt
pyrewriter.egg-info/top_level.txt
pyrewriter.egg-info/zip-safe