Metadata-Version: 1.0
Name: pyrewriter
Version: 0.1.58
Summary: pyrewriter v. 0.1.58
